{
  "input_path": "models/Topic-Modeling/data/rating.csv",
  "output_path": "models/Topic-Modeling/preprocessing/baseline_phase1/rating_normalized_phase6_ngram.csv",
  "text_col": "content",
  "loaded_docs": 1000,
  "final_docs": 999,
  "dropped_empty_docs": 1,
  "empty_docs_removed_pct": 0.1,
  "tokens_before_rare_filter": 17592,
  "tokens_after_rare_filter": 11162,
  "tokens_removed_by_rare_filter": 6430,
  "tokens_removed_by_rare_filter_pct": 36.5507,
  "vocab_size_before_filtering": 4824,
  "vocab_size_after_filtering": 821,
  "ngrams": {
    "enabled": true,
    "min_count": 15,
    "threshold": 10.0
  },
  "token_stats": {
    "mean": 11.173173173173174,
    "median": 11.0,
    "min": 1,
    "max": 24
  },
  "top_terms": [
    {
      "term": "char",
      "count": 969
    },
    {
      "term": "october",
      "count": 113
    },
    {
      "term": "country",
      "count": 80
    },
    {
      "term": "president",
      "count": 75
    },
    {
      "term": "company",
      "count": 74
    },
    {
      "term": "mexico",
      "count": 73
    },
    {
      "term": "china",
      "count": 71
    },
    {
      "term": "myanmar",
      "count": 65
    },
    {
      "term": "report",
      "count": 62
    },
    {
      "term": "international",
      "count": 56
    },
    {
      "term": "tuesday",
      "count": 55
    },
    {
      "term": "world",
      "count": 53
    },
    {
      "term": "africa",
      "count": 51
    },
    {
      "term": "group",
      "count": 48
    },
    {
      "term": "announce",
      "count": 47
    },
    {
      "term": "military",
      "count": 47
    },
    {
      "term": "wednesday",
      "count": 47
    },
    {
      "term": "national",
      "count": 46
    },
    {
      "term": "state",
      "count": 46
    },
    {
      "term": "monday",
      "count": 44
    },
    {
      "term": "city",
      "count": 42
    },
    {
      "term": "world_cup",
      "count": 39
    },
    {
      "term": "african",
      "count": 38
    },
    {
      "term": "south",
      "count": 38
    },
    {
      "term": "oct_globe",
      "count": 38
    }
  ]
}
